.travis.yml
CHANGES.txt
COPYRIGHT.txt
LICENSE.txt
MANIFEST.in
README.txt
TODO.txt
bootstrap.py
buildout.cfg
setup.py
src/refline/__init__.py
src/refline.srccheck.egg-info/PKG-INFO
src/refline.srccheck.egg-info/SOURCES.txt
src/refline.srccheck.egg-info/dependency_links.txt
src/refline.srccheck.egg-info/entry_points.txt
src/refline.srccheck.egg-info/namespace_packages.txt
src/refline.srccheck.egg-info/not-zip-safe
src/refline.srccheck.egg-info/requires.txt
src/refline.srccheck.egg-info/top_level.txt
src/refline/srccheck/README.txt
src/refline/srccheck/__init__.py
src/refline/srccheck/checker.py
src/refline/srccheck/pyflakes.py
src/refline/srccheck/tests.py
src/refline/srccheck/testing/__init__.py
src/refline/srccheck/testing/bad.css
src/refline/srccheck/testing/bad.py
src/refline/srccheck/testing/ignored_bad.py
src/refline/srccheck/testing/some.js
src/refline/srccheck/testing/z3c.form.po